sndid/__init__.py
sndid/__version__.py
sndid/alsa.py
sndid/analyzerwrapper.py
sndid/audiodetectionwriter.py
sndid/audiowriter.py
sndid/client.py
sndid/config.py
sndid/constants.py
sndid/detectionswriter.py
sndid/filecli.py
sndid/jack_lazy_loader.py
sndid/jackcli.py
sndid/jackmain.py
sndid/list.py
sndid/list.sh
sndid/segment_analyzer.py
sndid/server.py
sndid/server.sh
sndid/sndid-file.sh
sndid/sndidjack.py
sndid/stream.py
sndid/textdetectionwriter.py
sndid/textwriter.py
sndid-0.5.0.dist-info/LICENSE-apache.txt
sndid-0.5.0.dist-info/METADATA
sndid-0.5.0.dist-info/WHEEL
sndid-0.5.0.dist-info/entry_points.txt
sndid-0.5.0.dist-info/RECORD
