Metadata-Version: 2.1
Name: sndid
Version: 0.5.0
Summary: AI Sound Identification.
License: Apache-2.0
Author: Jeff Moe
Author-email: moe@parrot.codes
Requires-Python: >=3.10,<3.12
Classifier: Development Status :: 3 - Alpha
Classifier: Environment :: Console
Classifier: Intended Audience :: Developers
Classifier: Intended Audience :: Education
Classifier: Intended Audience :: Science/Research
Classifier: License :: OSI Approved :: Apache Software License
Classifier: Natural Language :: English
Classifier: Operating System :: POSIX :: Linux
Classifier: Programming Language :: Python :: 3
Classifier: Programming Language :: Python :: 3.10
Classifier: Programming Language :: Python :: 3.11
Classifier: Topic :: Education
Classifier: Topic :: Multimedia :: Sound/Audio :: Analysis
Classifier: Topic :: Multimedia :: Sound/Audio :: Capture/Recording
Classifier: Topic :: Scientific/Engineering :: Artificial Intelligence
Classifier: Topic :: Scientific/Engineering :: Bio-Informatics
Requires-Dist: JACK-Client
Requires-Dist: birdnetlib
Requires-Dist: gitpython
Requires-Dist: librosa
Requires-Dist: numpy
Requires-Dist: pydantic
Requires-Dist: pyyaml
Requires-Dist: scikit-learn
Requires-Dist: scipy
Requires-Dist: setuptools_scm
Requires-Dist: soundfile
Requires-Dist: tensorflow (==2.15.1)
Project-URL: changelog, https://spacecruft.org/deepcrayon/sndid/raw/branch/main/CHANGELOG.txt
Project-URL: documentation, https://sndid.ai
Project-URL: homepage, https://sndid.ai
Project-URL: issues, https://spacecruft.org/deepcrayon/sndid/issues
Project-URL: repository, https://spacecruft.org/deepcrayon/sndid
